tkmagicgrid/__init__.py
tkmagicgrid/__main__.py
tkmagicgrid/widget.py
tkMagicGrid-1.0.3.dist-info/LICENSE
tkMagicGrid-1.0.3.dist-info/METADATA
tkMagicGrid-1.0.3.dist-info/WHEEL
tkMagicGrid-1.0.3.dist-info/top_level.txt
tkMagicGrid-1.0.3.dist-info/RECORD
