Metadata-Version: 2.1
Name: tkMagicGrid
Version: 1.0.3
Summary: Table layout widget for Tkinter
Home-page: https://github.com/bmjcode/tkMagicGrid
Author: Benjamin Johnson
Author-email: bmjcode@gmail.com
License: UNKNOWN
Platform: UNKNOWN
Classifier: Development Status :: 4 - Beta
Classifier: Programming Language :: Python :: 2
Classifier: Programming Language :: Python :: 3
Classifier: License :: OSI Approved :: MIT License
Classifier: Operating System :: OS Independent
